{"Home & Beauty": 73.21999999999998, "Shoes": 12685.479999999994, "Books": 11137.339999999993, "Outdoors & Movies": 612.08, "Health": 13259.379999999997, "Home & Games": 712.1100000000001, "Outdoors": 11608.799999999997, "Jewelry": 11203.669999999996, "Garden": 12261.269999999999, "Health & Computers": 613.7499999999999, "Baby": 11579.189999999999, "Automotive & Movies": 808.4099999999999, "Electronics": 11701.189999999997, "Computers & Movies": 503.88, "Industrial & Music": 528.87, "Grocery & Outdoors": 303.73999999999995, "Shoes & Health": 419.39, "Home & Jewelry": 228.79999999999995, "Home": 10203.020000000002, "Automotive & Health": 922.75, "Computers": 11135.310000000001, "Health & Beauty": 533.84, "Automotive": 10998.730000000001, "Industrial & Electronics": 777.2199999999999, "Kids & Toys": 480.45, "Toys & Music": 405.09, "Grocery & Health": 690.44, "Tools & Baby": 678.9599999999999, "Computers & Grocery": 266.36, "Movies & Tools": 466.08, "Automotive & Sports": 1180.0100000000002, "Toys": 10180.049999999996, "Music & Electronics": 256.64, "Toys & Sports": 593.15, "Movies": 11213.089999999997, "Electronics & Books": 691.83, "Computers & Kids": 265.62, "Garden & Baby": 193.19, "Beauty": 11899.230000000018, "Health & Clothing": 521.7199999999999, "Tools & Garden": 742.1799999999998, "Tools": 9910.730000000001, "Kids & Tools": 726.2599999999999, "Music": 11030.61, "Baby & Health": 782.94, "Music & Jewelry": 532.3, "Kids": 11639.740000000002, "Shoes & Kids": 690.52, "Games": 12329.330000000009, "Baby & Tools": 492.30000000000007, "Health & Electronics": 561.14, "Sports & Baby": 825.6299999999998, "Jewelry & Kids": 448.15, "Clothing & Garden": 573.1700000000001, "Automotive & Baby": 1039.27, "Health & Tools": 832.49, "Garden & Industrial": 608.1, "Jewelry & Movies": 684.6, "Movies & Grocery": 654.3499999999999, "Baby & Industrial": 1132.7199999999998, "Shoes & Electronics": 525.29, "Games & Industrial": 579.8800000000001, "Movies & Garden": 453.7, "Games & Shoes": 606.35, "Clothing": 10709.45, "Music & Movies": 230.0, "Music & Books": 861.8200000000002, "Tools & Shoes": 321.32, "Sports & Music": 633.1199999999999, "Kids & Health": 980.8900000000001, "Garden & Tools": 332.33000000000004, "Home & Garden": 614.5299999999999, "Baby & Beauty": 447.7700000000001, "Computers & Outdoors": 399.95, "Jewelry & Games": 427.76, "Industrial & Baby": 605.6700000000001, "Outdoors & Clothing": 602.6700000000001, "Baby & Shoes": 431.19999999999993, "Tools & Home": 732.74, "Sports & Electronics": 620.91, "Grocery": 11428.9, "Kids & Grocery": 858.8, "Clothing & Music": 696.79, "Games & Clothing": 583.6, "Baby & Sports": 870.23, "Electronics & Shoes": 335.09, "Sports & Shoes": 833.6000000000001, "Electronics & Beauty": 642.2, "Automotive & Kids": 508.49, "Beauty & Clothing": 618.16, "Garden & Music": 748.7900000000001, "Jewelry & Grocery": 502.54999999999995, "Electronics & Baby": 371.2, "Health & Sports": 531.1299999999999, "Movies & Sports": 763.2800000000001, "Music & Shoes": 753.2800000000001, "Books & Shoes": 808.5600000000001, "Garden & Beauty": 331.66, "Electronics & Home": 560.77, "Clothing & Beauty": 824.7299999999999, "Home & Movies": 605.9, "Sports & Books": 579.3000000000001, "Books & Movies": 929.9600000000002, "Grocery & Jewelry": 682.8900000000001, "Outdoors & Beauty": 680.74, "Industrial": 10168.370000000004, "Computers & Baby": 382.1899999999999, "Baby & Movies": 771.87, "Toys & Jewelry": 852.7499999999999, "Books & Automotive": 1096.0900000000001, "Electronics & Kids": 361.69000000000005, "Jewelry & Outdoors": 739.7, "Sports": 11540.02999999999, "Computers & Beauty": 268.01, "Kids & Garden": 461.55, "Electronics & Toys": 547.98, "Music & Grocery": 609.88, "Tools & Grocery": 1118.09, "Home & Grocery": 535.15, "Games & Toys": 585.6, "Books & Baby": 457.0, "Automotive & Music": 580.0600000000001, "Outdoors & Games": 257.01, "Grocery & Kids": 473.93999999999994, "Tools & Beauty": 679.6600000000001, "Baby & Automotive": 683.95, "Baby & Clothing": 1129.79, "Movies & Kids": 211.14, "Industrial & Jewelry": 815.5700000000002, "Jewelry & Automotive": 522.71, "Movies & Jewelry": 581.04, "Outdoors & Industrial": 1030.5700000000002, "Electronics & Health": 394.48, "Home & Industrial": 638.49, "Clothing & Health": 311.15000000000003, "Shoes & Automotive": 468.85, "Books & Grocery": 572.83, "Shoes & Home": 544.03, "Jewelry & Home": 596.0600000000001, "Sports & Jewelry": 471.12999999999994, "Books & Computers": 341.12, "Movies & Electronics": 402.26, "Tools & Electronics": 564.69, "Movies & Outdoors": 321.78000000000003, "Music & Kids": 614.8699999999999, "Outdoors & Garden": 546.34, "Music & Outdoors": 664.88, "Music & Garden": 791.1700000000001, "Automotive & Beauty": 641.51, "Home & Tools": 626.99, "Computers & Shoes": 465.12, "Beauty & Music": 296.86999999999995, "Baby & Grocery": 577.18, "Clothing & Electronics": 691.03, "Baby & Music": 873.6500000000001, "Automotive & Tools": 1112.3899999999999, "Jewelry & Electronics": 427.2900000000001, "Baby & Jewelry": 420.27, "Outdoors & Kids": 705.03, "Outdoors & Baby": 558.19, "Grocery & Home": 352.87, "Games & Beauty": 474.63, "Clothing & Tools": 443.66, "Jewelry & Music": 621.49, "Games & Computers": 445.70000000000005, "Outdoors & Jewelry": 447.33000000000004, "Jewelry & Tools": 500.65000000000003, "Home & Books": 576.64, "Health & Music": 199.22, "Sports & Grocery": 418.5200000000001, "Automotive & Outdoors": 461.65, "Tools & Computers": 223.28, "Industrial & Clothing": 714.6199999999999, "Garden & Home": 466.44, "Home & Automotive": 397.27, "Toys & Health": 314.66, "Electronics & Grocery": 734.42, "Industrial & Garden": 689.1000000000001, "Industrial & Health": 769.41, "Kids & Baby": 470.96, "Movies & Automotive": 666.6999999999999, "Garden & Toys": 579.87, "Toys & Industrial": 727.55, "Shoes & Industrial": 603.21, "Computers & Electronics": 722.68, "Kids & Books": 359.41, "Grocery & Electronics": 675.1, "Electronics & Computers": 717.54, "Books & Garden": 629.8199999999999, "Jewelry & Books": 740.31, "Movies & Books": 892.6899999999999, "Computers & Toys": 547.05, "Health & Garden": 623.57, "Clothing & Grocery": 534.6899999999999, "Toys & Garden": 599.1300000000001, "Automotive & Shoes": 595.49, "Industrial & Games": 655.9899999999999, "Grocery & Automotive": 559.8199999999999, "Kids & Computers": 407.12999999999994, "Health & Industrial": 480.16, "Industrial & Computers": 673.85, "Shoes & Tools": 541.8, "Tools & Games": 553.93, "Tools & Sports": 517.99, "Health & Baby": 461.27, "Books & Home": 686.89, "Toys & Movies": 818.69, "Automotive & Grocery": 495.55000000000007, "Toys & Clothing": 634.5300000000001, "Industrial & Beauty": 445.86, "Jewelry & Clothing": 480.88, "Clothing & Kids": 634.9799999999999, "Industrial & Home": 478.21999999999997, "Games & Movies": 607.6100000000001, "Baby & Books": 389.0199999999999, "Grocery & Beauty": 938.03, "Books & Clothing": 567.58, "Books & Health": 698.41, "Electronics & Outdoors": 548.9200000000001, "Games & Electronics": 633.7900000000001, "Industrial & Tools": 533.03, "Outdoors & Music": 629.9200000000001, "Movies & Beauty": 584.09, "Garden & Kids": 445.92999999999995, "Toys & Baby": 473.97, "Tools & Toys": 825.45, "Industrial & Shoes": 655.26, "Tools & Jewelry": 306.72, "Sports & Automotive": 410.79999999999995, "Clothing & Games": 459.67, "Beauty & Garden": 738.2399999999999, "Outdoors & Sports": 820.3400000000001, "Home & Kids": 975.61, "Jewelry & Baby": 367.98, "Health & Toys": 235.89000000000001, "Tools & Kids": 626.8100000000001, "Tools & Health": 429.96, "Music & Computers": 776.0000000000001, "Clothing & Shoes": 432.11000000000007, "Beauty & Books": 375.32000000000005, "Health & Shoes": 533.0, "Grocery & Toys": 260.66999999999996, "Industrial & Grocery": 212.79999999999998, "Grocery & Movies": 663.4000000000001, "Automotive & Home": 690.8300000000002, "Automotive & Electronics": 470.0, "Computers & Books": 728.8800000000001, "Toys & Outdoors": 484.4, "Sports & Computers": 341.81, "Beauty & Grocery": 603.06, "Shoes & Garden": 980.4300000000001, "Books & Beauty": 491.54999999999995, "Health & Grocery": 949.14, "Tools & Books": 479.26000000000005, "Sports & Toys": 463.46, "Shoes & Baby": 349.37, "Kids & Shoes": 737.48, "Beauty & Kids": 593.35, "Clothing & Books": 459.37999999999994, "Books & Industrial": 625.98, "Movies & Games": 369.39, "Clothing & Toys": 398.08, "Industrial & Toys": 529.71, "Industrial & Kids": 584.3499999999999, "Games & Outdoors": 331.1, "Toys & Kids": 767.36, "Grocery & Sports": 349.94, "Books & Electronics": 597.9699999999999, "Games & Home": 517.66, "Shoes & Clothing": 585.27, "Shoes & Jewelry": 486.28000000000003, "Beauty & Games": 593.49, "Electronics & Sports": 370.09999999999997, "Beauty & Tools": 398.54999999999995, "Home & Music": 365.83, "Computers & Industrial": 350.00999999999993, "Games & Sports": 787.4699999999998, "Beauty & Health": 489.8799999999999, "Home & Clothing": 413.99999999999994, "Kids & Electronics": 284.54, "Music & Tools": 1015.35, "Garden & Health": 683.7299999999999, "Garden & Movies": 350.41, "Beauty & Computers": 653.1399999999999, "Automotive & Industrial": 876.9200000000001, "Beauty & Jewelry": 613.8399999999999, "Health & Jewelry": 931.06, "Games & Garden": 442.72, "Automotive & Games": 508.71, "Kids & Industrial": 732.9399999999999, "Music & Clothing": 362.77, "Computers & Garden": 782.53, "Sports & Health": 626.3799999999999, "Music & Toys": 606.98, "Kids & Music": 306.52000000000004, "Books & Sports": 1095.7, "Kids & Games": 645.9900000000001, "Grocery & Music": 504.62, "Automotive & Clothing": 573.87, "Garden & Books": 382.60999999999996, "Outdoors & Shoes": 669.1599999999999, "Health & Automotive": 996.1199999999999, "Beauty & Automotive": 238.13, "Toys & Home": 518.24, "Computers & Jewelry": 782.91, "Industrial & Outdoors": 683.36, "Garden & Outdoors": 389.83000000000004, "Movies & Music": 439.57000000000005, "Sports & Outdoors": 587.4699999999999, "Outdoors & Electronics": 711.0799999999999, "Health & Games": 644.09, "Books & Toys": 562.6399999999999, "Shoes & Outdoors": 590.39, "Baby & Kids": 648.6099999999999, "Electronics & Tools": 618.8400000000001, "Home & Sports": 369.25000000000006, "Electronics & Movies": 639.7300000000001, "Sports & Clothing": 462.55, "Movies & Home": 613.9, "Industrial & Movies": 295.3, "Computers & Sports": 311.76, "Computers & Home": 336.96999999999997, "Home & Outdoors": 299.01, "Games & Jewelry": 398.18000000000006, "Music & Home": 253.89, "Grocery & Garden": 380.25, "Jewelry & Industrial": 405.22, "Clothing & Sports": 732.8599999999999, "Jewelry & Computers": 545.8399999999999, "Computers & Automotive": 753.7499999999998, "Garden & Automotive": 542.24, "Toys & Automotive": 456.87, "Electronics & Industrial": 609.51, "Sports & Home": 522.3699999999999, "Automotive & Jewelry": 687.6600000000001, "Tools & Industrial": 604.6099999999999, "Beauty & Toys": 733.6199999999999, "Tools & Music": 397.13, "Home & Health": 622.31, "Jewelry & Toys": 414.2700000000001, "Kids & Movies": 384.03999999999996, "Garden & Shoes": 183.89999999999998, "Movies & Computers": 660.76, "Baby & Games": 431.34, "Electronics & Garden": 342.3, "Health & Books": 660.32, "Toys & Electronics": 905.7199999999999, "Automotive & Toys": 268.55, "Books & Kids": 541.7299999999999, "Clothing & Home": 392.91, "Games & Kids": 487.99, "Toys & Computers": 494.76, "Baby & Toys": 383.75, "Outdoors & Home": 640.39, "Sports & Industrial": 585.66, "Games & Grocery": 549.2800000000001, "Movies & Baby": 470.26, "Industrial & Automotive": 742.9999999999999, "Toys & Books": 451.34999999999997, "Movies & Clothing": 653.74, "Computers & Music": 632.33, "Movies & Toys": 108.64, "Outdoors & Grocery": 734.5799999999999, "Clothing & Industrial": 416.64, "Grocery & Books": 502.72, "Baby & Home": 638.4899999999999, "Automotive & Garden": 167.9, "Beauty & Electronics": 523.48, "Music & Health": 380.37, "Games & Music": 405.63, "Electronics & Jewelry": 775.1800000000001, "Industrial & Books": 329.87, "Books & Jewelry": 501.08, "Games & Tools": 618.7099999999999, "Home & Toys": 651.2800000000001, "Garden & Grocery": 306.05, "Kids & Jewelry": 509.61, "Tools & Movies": 543.42, "Garden & Games": 736.2599999999999, "Beauty & Movies": 651.4200000000001, "Movies & Industrial": 416.13, "Outdoors & Computers": 504.07, "Sports & Games": 541.9800000000001, "Games & Books": 714.4099999999999, "Toys & Beauty": 284.78999999999996, "Health & Outdoors": 300.81999999999994, "Games & Health": 276.40999999999997, "Books & Music": 591.95, "Sports & Beauty": 744.22, "Baby & Electronics": 279.55, "Computers & Health": 440.11, "Clothing & Outdoors": 534.34, "Jewelry & Health": 639.37, "Baby & Outdoors": 375.8, "Beauty & Shoes": 528.83, "Jewelry & Beauty": 542.05, "Health & Home": 597.01, "Kids & Automotive": 226.3, "Baby & Garden": 231.97, "Garden & Jewelry": 562.0799999999999, "Music & Beauty": 175.23999999999998, "Toys & Tools": 627.61, "Music & Games": 648.6000000000001, "Books & Games": 452.71999999999997, "Clothing & Movies": 420.68, "Grocery & Industrial": 246.7, "Health & Movies": 443.17999999999995, "Toys & Shoes": 399.02000000000004, "Computers & Games": 422.60999999999996, "Grocery & Computers": 474.0, "Electronics & Games": 602.68, "Clothing & Jewelry": 336.38, "Kids & Home": 658.1099999999999, "Sports & Garden": 471.34, "Toys & Grocery": 612.59, "Clothing & Automotive": 681.55, "Beauty & Home": 369.38, "Shoes & Movies": 397.38000000000005, "Industrial & Sports": 657.8299999999999, "Grocery & Games": 715.98, "Grocery & Tools": 156.45, "Jewelry & Garden": 426.33, "Automotive & Books": 615.46, "Grocery & Shoes": 764.3000000000001, "Sports & Movies": 648.0899999999999, "Home & Shoes": 458.6, "Garden & Sports": 374.65000000000003, "Toys & Games": 395.18, "Outdoors & Tools": 520.1, "Garden & Clothing": 420.4799999999999, "Jewelry & Shoes": 336.56, "Clothing & Baby": 445.03, "Electronics & Music": 361.63, "Shoes & Toys": 352.40999999999997, "Shoes & Books": 424.95000000000005, "Automotive & Computers": 390.32, "Outdoors & Books": 199.01, "Kids & Clothing": 500.93000000000006, "Games & Baby": 133.28, "Kids & Sports": 556.0, "Sports & Kids": 671.77, "Computers & Tools": 509.20000000000005, "Beauty & Outdoors": 469.57, "Tools & Clothing": 296.81, "Books & Tools": 692.3699999999999, "Garden & Computers": 659.8500000000001, "Home & Electronics": 226.06, "Electronics & Clothing": 589.89, "Shoes & Games": 333.59, "Home & Computers": 468.41, "Outdoors & Health": 346.0, "Sports & Tools": 357.21, "Outdoors & Toys": 455.68000000000006, "Movies & Health": 401.03, "Books & Outdoors": 352.26000000000005, "Music & Baby": 432.59999999999997, "Games & Automotive": 848.3699999999998, "Shoes & Music": 456.99, "Grocery & Clothing": 524.93, "Health & Kids": 544.2800000000001, "Electronics & Automotive": 445.82000000000005, "Shoes & Sports": 450.64, "Baby & Computers": 671.0, "Beauty & Industrial": 436.86, "Music & Industrial": 601.23, "Jewelry & Sports": 501.38, "Outdoors & Automotive": 316.35, "Tools & Automotive": 363.55, "Beauty & Baby": 320.15, "Movies & Shoes": 447.83000000000004, "Shoes & Beauty": 213.6, "Kids & Outdoors": 314.21, "Kids & Beauty": 506.22, "Beauty & Sports": 437.69999999999993, "Shoes & Grocery": 250.19, "Grocery & Baby": 324.17999999999995, "Tools & Outdoors": 330.66999999999996, "Clothing & Computers": 81.95, "Computers & Clothing": 225.64999999999998, "Music & Automotive": 402.09, "Home & Baby": 207.02, "Shoes & Computers": 222.52, "Garden & Electronics": 406.29, "Music & Sports": 114.0}